viewflow_rest/__init__.py
viewflow_rest/activations.py
viewflow_rest/edges.py
viewflow_rest/fields.py
viewflow_rest/flows.py
viewflow_rest/mixins.py
viewflow_rest/models.py
viewflow_rest/nodes.py
viewflow_rest/rest_extensions.py
viewflow_rest/signals.py
viewflow_rest/views.py
viewflow_rest-3.0.0.data/data/README.md/README.md
viewflow_rest-3.0.0.dist-info/LICENSE
viewflow_rest-3.0.0.dist-info/METADATA
viewflow_rest-3.0.0.dist-info/WHEEL
viewflow_rest-3.0.0.dist-info/top_level.txt
viewflow_rest-3.0.0.dist-info/RECORD
