Metadata-Version: 2.1
Name: viewflow-rest
Version: 3.0.0
Summary: viewlflow that support django rest framework
Home-page: https://github.com/ramwin/viewflow-rest
Author: Xiang Wang
Author-email: ramwin@qq.com
License: MIT
Keywords: viewflow django-rest-framework viewflow-rest
Classifier: Development Status :: 3 - Alpha
Classifier: Intended Audience :: Developers
Classifier: Topic :: Software Development :: Build Tools
Classifier: License :: OSI Approved :: MIT License
Classifier: Programming Language :: Python :: 3
License-File: LICENSE
Requires-Dist: django
Requires-Dist: djangorestframework
Requires-Dist: django-status-signal
